ssossh/__init__.py
ssossh/__main__.py
ssossh/config/__init__.py
ssossh/config/authservers.json
ssossh/config/authservers.json~
ssossh/config/__pycache__/__init__.cpython-37.pyc
ssossh/config/__pycache__/__init__.cpython-38.pyc
ssossh/templates/__init__.py
ssossh/templates/call_back.html
ssossh/templates/__pycache__/__init__.cpython-37.pyc
ssossh/templates/__pycache__/__init__.cpython-38.pyc
ssossh-0.0.4.dist-info/LICENSE
ssossh-0.0.4.dist-info/METADATA
ssossh-0.0.4.dist-info/WHEEL
ssossh-0.0.4.dist-info/entry_points.txt
ssossh-0.0.4.dist-info/top_level.txt
ssossh-0.0.4.dist-info/RECORD
